distributionPackage/VERSION
distributionPackage/__init__.py
distributionPackage/makePackage.py
distributionPackage/app/__init__.py
distributionPackage/app/arguments.py
distributionPackage/app/options.py
distributionPackage/app/tests/__init__.py
distributionPackage/app/tests/testAppendArgument.py
distributionPackage/app/tests/testManifestArgument.py
distributionPackage/app/tests/testOptions.py
distributionPackage/app/tests/testOutputArgument.py
distributionPackage/app/tests/testPackageArgument.py
distributionPackage/app/tests/testProjectRoot.py
distributionPackage/app/tests/testTarArgument.py
distributionPackage/app/tests/testZipArgument.py
distributionPackage/copyFromManifest/__init__.py
distributionPackage/copyFromManifest/app.py
distributionPackage/copyFromManifest/options.py
distributionPackage/copyFromManifest/options.pyi
distributionPackage/copyFromManifest/tests/__init__.py
distributionPackage/copyFromManifest/tests/testArguments.py
distributionPackage/copyFromManifest/tests/testCopyFromManifest.py
distributionPackage/package/__init__.py
distributionPackage/package/base.py
distributionPackage/package/directory.py
distributionPackage/package/interface.py
distributionPackage/package/package.py
distributionPackage/package/tarPackage.py
distributionPackage/package/zipPackage.py
distributionPackage/package/tests/__init__.py
distributionPackage/package/tests/testChangeDirectory.py
distributionPackage/package/tests/testPackage.py
distributionPackage/package/tests/testTarPackage.py
distributionPackage/package/tests/testZipPackage.py
distributionPackage/package/tests/utility.py
distributionPackage/tests/__init__.py
distributionPackage/tests/testMakePackage.py
distributionPackage/utility/__init__.py
distributionPackage/utility/multipleManifests.py
distributionPackage/utility/tests/__init__.py
distributionPackage/utility/tests/testCombineManifests.py
distributionPackage-0.8.0.dist-info/entry_points.txt
distributionPackage-0.8.0.dist-info/LICENSE
distributionPackage-0.8.0.dist-info/WHEEL
distributionPackage-0.8.0.dist-info/METADATA
distributionPackage-0.8.0.dist-info/RECORD
