Metadata-Version: 2.1
Name: distributionPackage
Version: 0.8.0
Summary: A packaging utility for creating packages of files for distribution based on a YAML manifest.
Home-page: https://gitlab.com/blueskyjunkie/distribution-package
License: UNKNOWN
Keywords: manifest package distribution file
Author: Russell Smiley
Author-email: im.russell.smiley@gmail.com
Requires-Python: >=3
Classifier: License :: OSI Approved :: GNU General Public License v3 or later (GPLv3+)
Requires-Dist: packageManifest
Requires-Dist: pygments; extra == "dev"
Provides-Extra: .none
Provides-Extra: dev
